[
  {
    "channel_id": "1454392989920006343",
    "channel_name": "pikinew",
    "user_id": "1454351763107745926",
    "user_name": "Pikinih",
    "pack_1": null,
    "pack_2": null,
    "pack_3": null,
    "pack_4": null,
    "reffund_pack_1": null,
    "reffund_pack_2": null,
    "reffund_pack_3": null,
    "reffund_pack_4": null
  },
  {
    "channel_id": "1456685933192675512",
    "channel_name": "hanadesu",
    "user_id": "1082308409224859689",
    "user_name": "AL-WAYNE",
    "pack_1": null,
    "pack_2": null,
    "pack_3": null,
    "pack_4": null,
    "reffund_pack_1": null,
    "reffund_pack_2": null,
    "reffund_pack_3": null,
    "reffund_pack_4": null
  },
  {
    "channel_id": "1457360022425309267",
    "channel_name": "hanadesu",
    "user_id": "1082308409224859689",
    "user_name": "AL-WAYNE",
    "pack_1": null,
    "pack_2": null,
    "pack_3": null,
    "pack_4": null,
    "reffund_pack_1": null,
    "reffund_pack_2": null,
    "reffund_pack_3": null,
    "reffund_pack_4": null
  },
  {
    "channel_id": "1458059338823237838",
    "channel_name": "dazaiaja",
    "user_id": "1455401255269695519",
    "user_name": "ZIDANE",
    "pack_1": null,
    "pack_2": null,
    "pack_3": null,
    "pack_4": null,
    "reffund_pack_1": null,
    "reffund_pack_2": null,
    "reffund_pack_3": null,
    "reffund_pack_4": null
  },
  {
    "channel_id": "1465175355496337512",
    "channel_name": "jeevanxborel",
    "user_id": "1304842094069682277",
    "user_name": "Jevanror",
    "pack_1": null,
    "pack_2": null,
    "pack_3": null,
    "pack_4": null,
    "reffund_pack_1": null,
    "reffund_pack_2": null,
    "reffund_pack_3": null,
    "reffund_pack_4": null
  },
  {
    "channel_id": "1467098898391892050",
    "channel_name": "ozuyu",
    "user_id": "792830406864142376",
    "user_name": "yilo",
    "pack_1": 1,
    "pack_2": null,
    "pack_3": 1,
    "pack_4": null,
    "reffund_pack_1": null,
    "reffund_pack_2": null,
    "reffund_pack_3": null,
    "reffund_pack_4": null
  },
  {
    "channel_id": "1468278701635665960",
    "channel_name": "woobb",
    "user_id": "695542848187269130",
    "user_name": "si owob",
    "pack_1": null,
    "pack_2": null,
    "pack_3": null,
    "pack_4": null,
    "reffund_pack_1": null,
    "reffund_pack_2": null,
    "reffund_pack_3": null,
    "reffund_pack_4": null
  },
  {
    "channel_id": "1476846676961525912",
    "channel_name": "jabrin",
    "user_id": "875742245674946602",
    "user_name": "jepri2",
    "pack_1": null,
    "pack_2": 2,
    "pack_3": null,
    "pack_4": null,
    "reffund_pack_1": null,
    "reffund_pack_2": null,
    "reffund_pack_3": null,
    "reffund_pack_4": null
  }
]
